{
    "wallpaper": "/home/bixer/wallpapers/Literal Wallpaper.png",
    "alpha": "100",
    "special": {
        "background": "#0a0a0a",
        "foreground": "#e5e8ee",
        "cursor": "#e5e8ee"
    },
    "colors": {
        "color0": "#0a0a0a",
        "color1": "#8F939A",
        "color2": "#A8ADB5",
        "color3": "#B7BCC5",
        "color4": "#BDC2CB",
        "color5": "#C9CED8",
        "color6": "#D5DBE6",
        "color7": "#e5e8ee",
        "color8": "#a0a2a6",
        "color9": "#8F939A",
        "color10": "#A8ADB5",
        "color11": "#B7BCC5",
        "color12": "#BDC2CB",
        "color13": "#C9CED8",
        "color14": "#D5DBE6",
        "color15": "#e5e8ee"
    }
}